Workbook

Sheet RESUMO GERAL
B3: RACIONAL DE INVESTIMENTO DA HOLDING EMPRESAS
B5: Empresas/ Investidores | C5: Brobond | D5: Jefferson | E5: Petrick | F5: Peixoto | G5: Total
B6: Expo Feiras | C6: =SUMIF('EMPRÉSTIMO BROBOND'!C:C,'RESUMO GERAL'!B6,'EMPRÉSTIMO BROBOND'!B:B) -> 0 | D6: =SUMIF('EMPRÉSTIMO PESSOAL JJEFFERSON'!C:C,'RESUMO GERAL'!B6,'EMPRÉSTIMO PESSOAL JJEFFERSON'!B:B) -> 41000 | E6: =SUMIF('EMPRÉSTIMO PESSOAL PETRICK'!C:C,'RESUMO GERAL'!B6,'EMPRÉSTIMO PESSOAL PETRICK'!B:B) -> 40000 | F6: =SUMIF('EMPRÉSTIMO PESSOAL PEIXOTO'!C:C,'RESUMO GERAL'!B6,'EMPRÉSTIMO PESSOAL PEIXOTO'!B:B) -> 40000 | G6: =SUM(C6:F6) -> 121000
B7: Brobond | C7: =SUMIF('EMPRÉSTIMO BROBOND'!C:C,'RESUMO GERAL'!B7,'EMPRÉSTIMO BROBOND'!B:B) -> 94147 | D7: =SUMIF('EMPRÉSTIMO PESSOAL JJEFFERSON'!C:C,'RESUMO GERAL'!B7,'EMPRÉSTIMO PESSOAL JJEFFERSON'!B:B) -> 26079 | E7: =SUMIF('EMPRÉSTIMO PESSOAL PETRICK'!C:C,'RESUMO GERAL'!B7,'EMPRÉSTIMO PESSOAL PETRICK'!B:B) -> 0 | F7: =SUMIF('EMPRÉSTIMO PESSOAL PEIXOTO'!C:C,'RESUMO GERAL'!B7,'EMPRÉSTIMO PESSOAL PEIXOTO'!B:B) -> 0 | G7: =SUM(C7:F7) -> 120226
B8: Nutrallis | C8: =SUMIF('EMPRÉSTIMO BROBOND'!C:C,'RESUMO GERAL'!B8,'EMPRÉSTIMO BROBOND'!B:B) -> 0 | D8: =SUMIF('EMPRÉSTIMO PESSOAL JJEFFERSON'!C:C,'RESUMO GERAL'!B8,'EMPRÉSTIMO PESSOAL JJEFFERSON'!B:B) -> 60400 | E8: =SUMIF('EMPRÉSTIMO PESSOAL PETRICK'!C:C,'RESUMO GERAL'!B8,'EMPRÉSTIMO PESSOAL PETRICK'!B:B) -> 59226.5 | F8: =SUMIF('EMPRÉSTIMO PESSOAL PEIXOTO'!C:C,'RESUMO GERAL'!B8,'EMPRÉSTIMO PESSOAL PEIXOTO'!B:B) -> 59226.5 | G8: =SUM(C8:F8) -> 178853
B9: TOTAL | C9: =SUM(C6:C8) -> 94147 | D9: =SUM(D6:D8) -> 127479 | E9: =SUM(E6:E8) -> 99226.5 | F9: =SUM(F6:F8) -> 99226.5 | G9: =SUM(G6:G8) -> 420079

Sheet EMPRÉSTIMO PESSOAL JJEFFERSON
A1: RACIONAL EMPRESTIMOS E INVESTIMENTO
B2: =SUBTOTAL(9,B4:B10) -> 111400 | H2: CREDOR | I2: Nome mês | J2: Mês | K2: Valor Inicial | L2: Juros | M2: Vlr Juros | N2: Valor +Jurso | O2: Dias Juros | P2: Pgto Realizado | Q2: Saldo Devedor | R2: Observação
A3: QUEM | B3: VALOR | C3: Detatlhes | D3: Mês Emp. | E3: Juros | F3: Descrição | I3: Outubro | J3: 1 | K3: =B5 -> 10000 | L3: 0.04 | M3: =IFERROR((K3*L3)/30*15," ") -> 200 | N3: =IF(O3="","",M3+K3) -> 10200 | O3: 15 | P3: 0 | Q3: =N3-P3 -> 10200 | S3: 2024
A4: JEFFERSON | B4: 11000 | C4: Expo Feiras | D4: 45566 | I4: Novembro | J4: 2 | K4: =Q3 -> 10200 | L4: 0.04 | M4: =IFERROR((K4*L4),"") -> 408 | N4: =IF(O4="","",M4+K4) -> 10608 | O4: 30 | P4: 0 | Q4: =N4-P4 -> 10608 | S4: 2024
A5: AMIGA MAMAE | B5: 10000 | C5: Expo Feiras | D5: 45658 | E5: 0.04 | F5: Pagamento com juros de 4% | I5: Dezembro | J5: 3 | K5: =Q4 -> 10608 | L5: 0.04 | M5: =IFERROR((K5*L5),"") -> 424.32 | N5: =IF(O5="","",M5+K5) -> 11032.32 | O5: 30 | P5: 0 | Q5: =N5-P5 -> 11032.32 | S5: 2024
A6: TIO ELSON | B6: 10000 | C6: Brobond Capital | D6: 45658 | E6: 0.05 | F6: Pagamento com juros de 5% | I6: Janeiro | J6: 4 | K6: =Q5 -> 11032.32 | L6: 0.04 | M6: =IFERROR((K6*L6),"") -> 441.2928 | N6: =IF(O6="","",M6+K6) -> 11473.613 | O6: 30 | P6: 0 | Q6: =N6-P6 -> 11473.613 | S6: 2025
A7: FLÁVIA | B7: 10000 | C7: Expo Feiras | D7: 45566 | E7: 0.02 | F7: Pagamento com juros de 2% | I7: Fevereiro | J7: 5 | K7: =Q6 -> 11473.613 | L7: 0.04 | M7: =IFERROR((K7*L7),"") -> 458.94451 | N7: =IF(O7="","",M7+K7) -> 11932.557 | O7: 30 | P7: 1650 | Q7: =N7-P7 -> 10282.557 | R7: Dia 06/02 R$ 800,00 e 20/02 R$ 850,00 | S7: 2025
A8: FLÁVIA | B8: 10000 | C8: Expo Feiras | D8: 45627 | E8: 0.02 | F8: Pagamento com juros de 2% | I8: Março | J8: 6 | K8: =Q7 -> 10282.557 | L8: 0.04 | M8: =IFERROR((K8*L8),"") -> 411.30229 | N8: =IF(O8="","",M8+K8) -> 10693.86 | O8: 30 | P8: 150 | Q8: =N8-P8 -> 10543.86 | R8: Dia 06/03 R$ 150,00 | S8: 2025
A9: PETRICK E PEIXOTO | B9: 30800 | C9: Nutrallis | D9: 45870 | E9: 0.015 | F9: Juros de 1,5% valor 50% Peixto 50$ Petrick | I9: Abril | J9: 7 | K9: =Q8 -> 10543.86 | L9: 0.04 | M9: =IFERROR((K9*L9),"") -> 421.75438 | N9: =IF(O9="","",M9+K9) -> 10965.614 | O9: 30 | P9: 0 | Q9: =N9-P9 -> 10965.614 | S9: 2025
A10: FLÁVIA ROSA PESSOAL | B10: =32000-2400 -> 29600 | C10: Nutrallis | D10: 45901 | E10: 0.03 | F10: Juros de 2% | I10: Maio | J10: 8 | K10: =Q9 -> 10965.614 | L10: 0.04 | M10: =IFERROR((K10*L10),"") -> 438.62456 | N10: =IF(O10="","",M10+K10) -> 11404.239 | O10: 30 | P10: 0 | Q10: =N10-P10 -> 11404.239 | S10: 2025 | W10: =Y12 -> 3457 | AA10: Principal
I11: Junho | J11: 9 | K11: =Q10 -> 11404.239 | L11: 0.04 | M11: =IFERROR((K11*L11),"") -> 456.16954 | N11: =IF(O11="","",M11+K11) -> 11860.408 | O11: 30 | P11: 0 | Q11: =N11-P11 -> 11860.408 | S11: 2025 | W11: =W10-N10 -> -7947.2385 | Y11: Pago | AA11: 10000
A12: TOTAL | B12: =SUM(B4:B10) -> 111400 | I12: Julho | J12: 10 | K12: =Q11 -> 11860.408 | L12: 0.04 | M12: =IFERROR((K12*L12),"") -> 474.41632 | N12: =IF(O12="","",M12+K12) -> 12334.824 | O12: 30 | P12: 0 | Q12: =N12-P12 -> 12334.824 | S12: 2025 | Y12: 3457 | Z12: =N30-Y12 -> 12903.575 | AA12: =N14-AA11 -> 3341.3461
I13: Agosto | J13: 11 | K13: =Q12 -> 12334.824 | L13: 0.04 | M13: =IFERROR((K13*L13),"") -> 493.39298 | N13: =IF(O13="","",M13+K13) -> 12828.217 | O13: 30 | P13: 0 | Q13: =N13-P13 -> 12828.217 | S13: 2025
I14: Setembro | J14: 12 | K14: =Q13 -> 12828.217 | L14: 0.04 | M14: =IFERROR((K14*L14),"") -> 513.1287 | N14: =IF(O14="","",M14+K14) -> 13341.346 | O14: 30 | P14: 0 | Q14: =N14-P14 -> 13341.346 | S14: 2025
I15: Outubro | J15: 13 | K15: =Q14 -> 13341.346 | L15: 0.04 | M15: =IFERROR((K15*L15),"") -> 533.65384 | N15: =IF(O15="","",M15+K15) -> 13875 | O15: 30 | P15: 0 | Q15: =N15-P15 -> 13875 | S15: 2025
I16: Novembro | J16: 14 | K16: =Q15 -> 13875 | L16: 0.04 | M16: =IFERROR((K16*L16),"") -> 555 | N16: =IF(O16="","",M16+K16) -> 14430 | O16: 30 | P16: 1500 | Q16: =N16-P16 -> 12930 | R16: Dia 03/11 R$ 1.000,00 e 14/11 R$ 500,00 | S16: 2025
I17: Dezembro | J17: 15 | K17: =Q16 -> 12930 | L17: 0.04 | M17: =IFERROR((K17*L17),"") -> 517.2 | N17: =IF(O17="","",M17+K17) -> 13447.2 | O17: 30 | P17: 0 | Q17: =N17-P17 -> 13447.2 | S17: 2025
I18: Janeiro | J18: 16 | K18: =Q17 -> 13447.2 | L18: 0.04 | M18: =IFERROR((K18*L18),"") -> 537.888 | N18: =IF(O18="","",M18+K18) -> 13985.088 | O18: 30 | P18: 0 | Q18: =N18-P18 -> 13985.088 | S18: 2026
I19: Fevereiro | J19: 17 | K19: =Q18 -> 13985.088 | L19: 0.04 | M19: =IFERROR((K19*L19),"") -> 559.40352 | N19: =IF(O19="","",M19+K19) -> 14544.491 | O19: 30 | P19: 0 | Q19: =N19-P19 -> 14544.491 | S19: 2026
I20: Março | J20: 19 | K20: =Q19 -> 14544.491 | L20: 0.04 | M20: =IFERROR((K20*L20),"") -> 581.77966 | N20: =IF(O20="","",M20+K20) -> 15126.271 | O20: 30 | P20: 0 | Q20: =N20-P20 -> 15126.271 | S20: 2026
I21: Abril | J21: 20 | K21: =Q20 -> 15126.271 | L21: 0.04 | M21: =IFERROR((K21*L21),"") -> 605.05084 | N21: =IF(O21="","",M21+K21) -> 15731.322 | O21: 30 | P21: 0 | Q21: =N21-P21 -> 15731.322 | S21: 2026
I22: Maio | J22: 21 | K22: =Q21 -> 15731.322 | L22: 0.04 | M22: =IFERROR((K22*L22),"") -> 629.25288 | N22: =IF(O22="","",M22+K22) -> 16360.575 | O22: 30 | P22: 1100 | Q22: =N22-P22 -> 15260.575 | S22: 2026
A23: QUEM | B23: VALOR Á PAGAR | I23: Junho | J23: 22 | K23: =Q22 -> 15260.575 | L23: 0.04 | M23: =IFERROR((K23*L23),"") -> 610.42299 | N23: =IF(O23="","",M23+K23) -> 15870.998 | O23: 30 | P23: 0 | Q23: =N23-P23 -> 15870.998 | S23: 2026
I24: Julho | J24: 23 | K24: =Q23 -> 15870.998 | L24: 0.04 | M24: =IFERROR((K24*L24),"") -> 634.83991 | N24: =IF(O24="","",M24+K24) -> 16505.838 | O24: 30 | P24: 0 | S24: 2026
I25: Agosto | J25: 24 | K25: =Q24 -> 0 | L25: 0.04 | M25: =IFERROR((K25*L25),"") -> 0 | N25: =IF(O25="","",M25+K25) -> 0 | O25: 30 | P25: 0 | S25: 2026
I26: Setembro | J26: 25 | K26: =Q25 -> 0 | L26: 0.04 | M26: =IFERROR((K26*L26),"") -> 0 | N26: =IF(O26="","",M26+K26) -> 0 | O26: 30 | P26: 0 | S26: 2026
I27: Outubro | J27: 26 | K27: =Q26 -> 0 | L27: 0.04 | M27: =IFERROR((K27*L27),"") -> 0 | N27: =IF(O27="","",M27+K27) -> 0 | O27: 30 | P27: 0 | S27: 2026
I28: Novembro | J28: 27 | K28: =Q27 -> 0 | L28: 0.04 | M28: =IFERROR((K28*L28),"") -> 0 | N28: =IF(O28="","",M28+K28) -> 0 | O28: 30 | P28: 0 | S28: 2026
I29: Dezembro | J29: 28 | K29: =Q28 -> 0 | L29: 0.04 | M29: =IFERROR((K29*L29),"") -> 0 | N29: =IF(O29="","",M29+K29) -> 0 | O29: 30 | P29: 0 | S29: 2026
A30: AMIGA MAMAE | B30: =SUMIF(H:H,A30,N:N) -> 16360.575 | D30: 185 | E30: 3 | F30: =D30*E30 -> 555 | H30: =A5 -> AMIGA MAMAE | I30: TOTAL | N30: =LARGE(N3:N23,1) -> 16360.575 | O30: =SUM(O3:O23) -> 615 | P30: =SUM(P3:P23) -> 4400
A31: TIO ELSON | B31: =SUMIF(H:H,A31,N:N) -> 14049.974 | D31: 144 | E31: 3 | F31: =D31*E31 -> 432
A32: FLÁVIA | B32: =SUMIF(H:H,A32,N:N) -> 45775.848 | D32: 346 | E32: 2 | F32: =D32*E32 -> 692
A33: PETRICK E PEIXOTO | B33: =SUMIF(H:H,A33,N:N) -> 33012.058 | F33: =SUM(F30:F32) -> 1679 | H33: CREDOR | I33: Nome mês | J33: Mês | K33: Valor Inicial | L33: Juros | M33: Vlr Juros | N33: Valor Final | O33: Dt Vlor Final
A34: TT EMPRÉSTIMO PESSOAL | B34: =SUM(B30:B33) -> 109198.46 | I34: Janeiro | J34: 1 | K34: =B6 -> 10000 | L34: 0.03 | M34: =IFERROR((K34*L34)/30*15," ") -> 150 | N34: =IF(O34="","",M34+K34) -> 10150 | O34: 45777
I35: Fevereiro | J35: 2 | K35: =N34 -> 10150 | L35: 0.03 | M35: =IFERROR((K35*L35),"") -> 304.5 | N35: =IF(O35="","",M35+K35) -> 10454.5 | O35: =SUM(O34+30) -> 45807
I36: Março | J36: 3 | K36: =N35 -> 10454.5 | L36: 0.03 | M36: =IFERROR((K36*L36),"") -> 313.635 | N36: =IF(O36="","",M36+K36) -> 10768.135 | O36: =SUM(O35+30) -> 45837
I37: Abril | J37: 4 | K37: =N36 -> 10768.135 | L37: 0.03 | M37: =IFERROR((K37*L37),"") -> 323.04405 | N37: =IF(O37="","",M37+K37) -> 11091.179 | O37: =SUM(O36+30) -> 45867
A38: QUEM | B38: VALOR | C38: Detatlhes | D38: Mês Emp. | I38: Maio | J38: 5 | K38: =N37 -> 11091.179 | L38: 0.03 | M38: =IFERROR((K38*L38),"") -> 332.73537 | N38: =IF(O38="","",M38+K38) -> 11423.914 | O38: =SUM(O37+30) -> 45897
A39: FLÁVIA | B39: 20000 | C39: EVENTOS | D39: 45566 | I39: Junho | J39: 6 | K39: =N38 -> 11423.914 | L39: 0.03 | M39: =IFERROR((K39*L39),"") -> 342.71743 | N39: =IF(O39="","",M39+K39) -> 11766.632 | O39: =SUM(O38+30) -> 45927
A40: FLÁVIA | B40: 5000 | C40: BROBOND | D40: 45717 | I40: Julho | J40: 7 | K40: =N39 -> 11766.632 | L40: 0.03 | M40: =IFERROR((K40*L40),"") -> 352.99896 | N40: =IF(O40="","",M40+K40) -> 12119.631 | O40: =SUM(O39+30) -> 45957
A41: FLÁVIA | B41: 15000 | C41: BROBOND | D41: 45825 | I41: Agosto | J41: 8 | K41: =N40 -> 12119.631 | L41: 0.03 | M41: =IFERROR((K41*L41),"") -> 363.58892 | N41: =IF(O41="","",M41+K41) -> 12483.22 | O41: =SUM(O40+30) -> 45987
A42: FLÁVIA | B42: 2400 | C42: BROBOND | D42: 45931 | I42: Setembro | J42: 9 | K42: =N41 -> 12483.22 | L42: 0.03 | M42: =IFERROR((K42*L42),"") -> 374.49659 | N42: =IF(O42="","",M42+K42) -> 12857.716 | O42: =SUM(O41+30) -> 46017
A43: FLAVIA CARTÃO | B43: 2000 | C43: CARTÃO PARA AGENCIA | D43: 45924 | I43: Outubro | J43: 10 | K43: =N42 -> 12857.716 | L43: 0.03 | M43: =IFERROR((K43*L43),"") -> 385.73149 | N43: =IF(O43="","",M43+K43) -> 13243.448 | O43: =SUM(O42+30) -> 46047
A44: FLAVIA CARTÃO | B44: 1600 | C44: CARTÃO PARA AGENCIA | D44: 45931 | I44: Novembro | J44: 11 | K44: =N43 -> 13243.448 | L44: 0.03 | M44: =IFERROR((K44*L44),"") -> 397.30343 | N44: =IF(O44="","",M44+K44) -> 13640.751 | O44: =SUM(O43+30) -> 46077
A45: CARTÃO FLAVIA | B45: 600 | C45: CARTÃO PARA AGENCIA | D45: 45964 | I45: Dezembro | J45: 12 | K45: =N44 -> 13640.751 | L45: 0.03 | M45: =IFERROR((K45*L45),"") -> 409.22254 | N45: =IF(O45="","",M45+K45) -> 14049.974 | O45: =SUM(O44+30) -> 46107
A46: CARTÃO FLAVIA | B46: 1679 | C46: BROBOND | D46: 45964 | I46: Janeiro | J46: 13 | K46: =N45 -> 14049.974 | L46: 0.03 | M46: =IFERROR((K46*L46),"") -> 421.49921 | N46: =IF(O46="","",M46+K46) -> 14471.473 | O46: =SUM(O45+30) -> 46137
A47: REFEIÇÕES MERCADO | B47: 2000 | C47: BROBOND | D47: Maio Tres meses +dois meses atrás | I47: Fevereiro | J47: 14 | K47: =N46 -> 14471.473 | L47: 0.03 | M47: =IFERROR((K47*L47),"") -> 434.14419 | N47: =IF(O47="","",M47+K47) -> 14905.617 | O47: =SUM(O46+30) -> 46167
I48: Março | J48: 15 | K48: =N47 -> 14905.617 | L48: 0.03 | M48: =IFERROR((K48*L48),"") -> 447.16852 | N48: =IF(O48="","",M48+K48) -> 15352.786 | O48: =SUM(O47+30) -> 46197
I49: Abril | J49: 16 | K49: =N48 -> 15352.786 | L49: 0.03 | M49: =IFERROR((K49*L49),"") -> 460.58357 | N49: =IF(O49="","",M49+K49) -> 15813.369 | O49: =SUM(O48+30) -> 46227
I50: Maio | J50: 17 | K50: =N49 -> 15813.369 | L50: 0.03 | M50: =IFERROR((K50*L50),"") -> 474.40108 | N50: =IF(O50="","",M50+K50) -> 16287.77 | O50: =SUM(O49+30) -> 46257
I51: Junho | J51: 18 | K51: =N50 -> 16287.77 | L51: 0.03 | M51: =IFERROR((K51*L51),"") -> 488.63311 | N51: =IF(O51="","",M51+K51) -> 16776.403 | O51: =SUM(O50+30) -> 46287
I52: Julho | J52: 19 | K52: =N51 -> 16776.403 | L52: 0.03 | M52: =IFERROR((K52*L52),"") -> 503.2921 | N52: =IF(O52="","",M52+K52) -> 17279.696 | O52: =SUM(O51+30) -> 46317
I53: Agosto | J53: 20 | K53: =N52 -> 17279.696 | L53: 0.03 | M53: =IFERROR((K53*L53),"") -> 518.39087 | N53: =IF(O53="","",M53+K53) -> 17798.086 | O53: =SUM(O52+30) -> 46347
I54: Setembro | J54: 21 | K54: =N53 -> 17798.086 | L54: 0.03 | M54: =IFERROR((K54*L54),"") -> 533.94259 | N54: =IF(O54="","",M54+K54) -> 18332.029 | O54: =SUM(O53+30) -> 46377
I55: Outubro | J55: 22 | K55: =N54 -> 18332.029 | L55: 0.03 | M55: =IFERROR((K55*L55),"") -> 549.96087 | N55: =IF(O55="","",M55+K55) -> 18881.99 | O55: =SUM(O54+30) -> 46407
I56: Novembro | J56: 23 | K56: =N55 -> 18881.99 | L56: 0.03 | M56: =IFERROR((K56*L56),"") -> 566.4597 | N56: =IF(O56="","",M56+K56) -> 19448.45 | O56: =SUM(O55+30) -> 46437
I57: Dezembro | J57: 24 | K57: =N56 -> 19448.45 | L57: 0.03 | M57: =IFERROR((K57*L57),"") -> 583.45349 | N57: =IF(O57="","",M57+K57) -> 20031.903 | O57: =SUM(O56+30) -> 46467
H58: =A6 -> TIO ELSON | I58: TOTAL | N58: =LARGE(N36:N45,1) -> 14049.974
A60: RACIONAL DESTIVO VALOR FINANCEIRO
A61: EVENTOS | B61: =SUMIF($C$39:$C$57,$A61,$B$39:$B$57) -> 20000 | H61: CREDOR | I61: Nome mês | J61: Mês | K61: Valor Inicial | L61: Juros | M61: Vlr Juros | N61: Valor Final | O61: Dt Vlor Final
A62: BROBOND | B62: =SUMIF($C$39:$C$57,$A62,$B$39:$B$57) -> 26079 | I62: Janeiro | J62: 1 | K62: =B7 -> 10000 | L62: 0.03 | M62: =IFERROR((K62*L62)/30*15," ") -> 150 | N62: =IF(O62="","",M62+K62) -> 10150 | O62: 45777
A63: CARTÃO PARA AGENCIA | B63: =SUMIF($C$39:$C$57,$A63,$B$39:$B$57) -> 4200 | I63: Fevereiro | J63: 2 | K63: =N62 -> 10150 | L63: 0.03 | M63: =IFERROR((K63*L63),"") -> 304.5 | N63: =IF(O63="","",M63+K63) -> 10454.5 | O63: =SUM(O62+30) -> 45807
I64: Março | J64: 3 | K64: =N63 -> 10454.5 | L64: 0.03 | M64: =IFERROR((K64*L64),"") -> 313.635 | N64: =IF(O64="","",M64+K64) -> 10768.135 | O64: =SUM(O63+30) -> 45837
A65: TOTAL GERAL DEVIDO | B65: =SUM(B61:B64) -> 50279 | I65: Abril | J65: 4 | K65: =N64 -> 10768.135 | L65: 0.03 | M65: =IFERROR((K65*L65),"") -> 323.04405 | N65: =IF(O65="","",M65+K65) -> 11091.179 | O65: =SUM(O64+30) -> 45867
I66: Maio | J66: 5 | K66: =N65 -> 11091.179 | L66: 0.03 | M66: =IFERROR((K66*L66),"") -> 332.73537 | N66: =IF(O66="","",M66+K66) -> 11423.914 | O66: =SUM(O65+30) -> 45897
A67: Emprestimos flávia | I67: Junho | J67: 6 | K67: =N66 -> 11423.914 | L67: 0.03 | M67: =IFERROR((K67*L67),"") -> 342.71743 | N67: =IF(O67="","",M67+K67) -> 11766.632 | O67: =SUM(O66+30) -> 45927
A68: DATA EMPRÉSTIMO | B68: VALOR | I68: Julho | J68: 7 | K68: =N67 -> 11766.632 | L68: 0.03 | M68: =IFERROR((K68*L68),"") -> 352.99896 | N68: =IF(O68="","",M68+K68) -> 12119.631 | O68: =SUM(O67+30) -> 45957
A69: 45566 | B69: 20000 | C69: Flavia e Daniel | I69: Agosto | J69: 8 | K69: =N68 -> 12119.631 | L69: 0.03 | M69: =IFERROR((K69*L69),"") -> 363.58892 | N69: =IF(O69="","",M69+K69) -> 12483.22 | O69: =SUM(O68+30) -> 45987
A70: 45733 | B70: 5000 | C70: Flavia e Daniel | I70: Setembro | J70: 9 | K70: =N69 -> 12483.22 | L70: 0.03 | M70: =IFERROR((K70*L70),"") -> 374.49659 | N70: =IF(O70="","",M70+K70) -> 12857.716 | O70: =SUM(O69+30) -> 46017
A71: 45800 | B71: 7000 | C71: Daniel Canhete | I71: Outubro | J71: 10 | K71: =N70 -> 12857.716 | L71: 0.03 | M71: =IFERROR((K71*L71),"") -> 385.73149 | N71: =IF(O71="","",M71+K71) -> 13243.448 | O71: =SUM(O70+30) -> 46047
A72: 45822 | B72: 8000 | C72: Daniel Canhete | I72: Novembro | J72: 11 | K72: =N71 -> 13243.448 | L72: 0.03 | M72: =IFERROR((K72*L72),"") -> 397.30343 | N72: =IF(O72="","",M72+K72) -> 13640.751 | O72: =SUM(O71+30) -> 46077
A73: 45918 | B73: 9800 | C73: Daniel Canhete | I73: Dezembro | J73: 12 | K73: =N72 -> 13640.751 | L73: 0.03 | M73: =IFERROR((K73*L73),"") -> 409.22254 | N73: =IF(O73="","",M73+K73) -> 14049.974 | O73: =SUM(O72+30) -> 46107
A74: 45918 | B74: 10000 | C74: Flavia Rosa
A75: 45918 | B75: 2400 | C75: Daniel Canhete
A76: 45924 | B76: 9800 | C76: Daniel Canhete
A77: TOTAL | B77: =SUM(B69:B76) -> 72000 | H77: =A7 -> FLÁVIA | I77: TOTAL | N77: =LARGE(N64:N73,1) -> 14049.974
H80: CREDOR | I80: Nome mês | J80: Mês | K80: Valor Inicial | L80: Juros | M80: Vlr Juros | N80: Valor Final | O80: Dt Vlor Final
I81: Agosto | J81: 1 | K81: =B9 -> 30800 | L81: 0.02 | M81: =IFERROR((K81*L81)/30*15," ") -> 308 | N81: =IF(O81="","",M81+K81) -> 31108 | O81: 45777
I82: Setembro | J82: 2 | K82: =N81 -> 31108 | L82: 0.02 | M82: =IFERROR((K82*L82),"") -> 622.16 | N82: =IF(O82="","",M82+K82) -> 31730.16 | O82: =SUM(O81+30) -> 45807
I83: Outubro | J83: 3 | K83: =N82 -> 31730.16 | L83: 0.02 | M83: =IFERROR((K83*L83),"") -> 634.6032 | N83: =IF(O83="","",M83+K83) -> 32364.763 | O83: =SUM(O82+30) -> 45837
I84: Novembro | J84: 4 | K84: =N83 -> 32364.763 | L84: 0.02 | M84: =IFERROR((K84*L84),"") -> 647.29526 | N84: =IF(O84="","",M84+K84) -> 33012.058 | O84: =SUM(O83+30) -> 45867
H88: =A33 -> PETRICK E PEIXOTO | I88: TOTAL | N88: =N84 -> 33012.058
K89: Peixoto | N89: =N88/2 -> 16506.029
K90: Petrick | N90: =N88/2 -> 16506.029
H95: CREDOR | I95: Nome mês | J95: Mês | K95: Valor Inicial | L95: Juros | M95: Vlr Juros | N95: Valor Final | O95: Dt Vlor Final
I96: Outubro | J96: 1 | K96: =B10 -> 29600 | L96: 0.02 | M96: =IFERROR((K96*L96)/30*15," ") -> 296 | N96: =IF(O96="","",M96+K96) -> 29896 | O96: 45930
I97: Novembro | J97: 2 | K97: =N96 -> 29896 | L97: =L96 -> 0.02 | M97: =IFERROR((K97*L97),"") -> 597.92 | N97: =IF(O97="","",M97+K97) -> 30493.92 | O97: =SUM(O96+30) -> 45960
I98: Dezembro | J98: 3 | K98: =N97 -> 30493.92 | L98: =L97 -> 0.02 | M98: =IFERROR((K98*L98),"") -> 609.8784 | N98: =IF(O98="","",M98+K98) -> 31103.798 | O98: =SUM(O97+30) -> 45990
I99: Janeiro | J99: 4 | K99: =N98 -> 31103.798 | L99: =L98 -> 0.02 | M99: =IFERROR((K99*L99),"") -> 622.07597 | N99: =IF(O99="","",M99+K99) -> 31725.874 | O99: =SUM(O98+30) -> 46020
H103: =A32 -> FLÁVIA | I103: TOTAL | N103: =N99 -> 31725.874

Sheet EMPRÉSTIMO PESSOAL PETRICK
A1: RACIONAL EMPRESTIMOS E INVESTIMENTO
G2: CREDOR | H2: Nome mês | I2: Mês | J2: Valor Inicial | K2: Juros | L2: Vlr Juros | M2: Valor Final | N2: Dt Vlor Final
A3: QUEM | B3: VALOR | C3: Detatlhes | D3: Mês Emp. | E3: Descrição | H3: 45931 | I3: 1 | J3: =B4 -> 40000 | K3: 0.01 | L3: =IFERROR((J3*K3)/30*15," ") -> 200 | M3: =IF(N3="","",L3+J3) -> 40200 | N3: 45595
A4: PETRICK PESSOAL | B4: 40000 | C4: Expo Feiras | D4: 45931 | E4: Pagamento com juros de 1% | H4: 45962 | I4: 2 | J4: =M3 -> 40200 | K4: 0.01 | L4: =IFERROR((J4*K4),"") -> 402 | M4: =IF(N4="","",L4+J4) -> 40602 | N4: =SUM(N3+30) -> 45625
A5: PETRICK (MÃE) | B5: 30801 | C5: Nutrallis | D5: 45870 | E5: Pagamento sem juros 1,5% | H5: 45992 | I5: 3 | J5: =M4 -> 40602 | K5: 0.01 | L5: =IFERROR((J5*K5),"") -> 406.02 | M5: =IF(N5="","",L5+J5) -> 41008.02 | N5: =SUM(N4+30) -> 45655
A6: PETRICK JEFF (MÃE) | B6: 15400 | C6: Nutrallis 1ª Formulas | D6: 45870 | H6: 46023 | I6: 4 | J6: =M5 -> 41008.02 | K6: 0.01 | L6: =IFERROR((J6*K6),"") -> 410.0802 | M6: =IF(N6="","",L6+J6) -> 41418.1 | N6: =SUM(N5+30) -> 45685
A7: PETRICK (MÃE) | B7: 28425.5 | C7: Nutrallis | D7: 45901 | H7: 46054 | I7: 5 | J7: =M6 -> 41418.1 | K7: 0.01 | L7: =IFERROR((J7*K7),"") -> 414.181 | M7: =IF(N7="","",L7+J7) -> 41832.281 | N7: =SUM(N6+30) -> 45715
A8: PETRICK PESSOAL | B8: 10000 | C8: Brobond capital | H8: 46082 | I8: 6 | J8: =M7 -> 41832.281 | K8: 0.01 | L8: =IFERROR((J8*K8),"") -> 418.32281 | M8: =IF(N8="","",L8+J8) -> 42250.604 | N8: =SUM(N7+30) -> 45745
A9: TOTAL | B9: =SUM(B4:B5)+B7 -> 99226.5 | H9: 46113 | I9: 7 | J9: =M8 -> 42250.604 | K9: 0.01 | L9: =IFERROR((J9*K9),"") -> 422.50604 | M9: =IF(N9="","",L9+J9) -> 42673.11 | N9: =SUM(N8+30) -> 45775
H10: 46143 | I10: 8 | J10: =M9 -> 42673.11 | K10: 0.01 | L10: =IFERROR((J10*K10),"") -> 426.7311 | M10: =IF(N10="","",L10+J10) -> 43099.841 | N10: =SUM(N9+30) -> 45805
H11: 46174 | I11: 9 | J11: =M10 -> 43099.841 | K11: 0.01 | L11: =IFERROR((J11*K11),"") -> 430.99841 | M11: =IF(N11="","",L11+J11) -> 43530.84 | N11: =SUM(N10+30) -> 45835
A12: QUEM | B12: VALOR Á PAGAR | H12: 46204 | I12: 10 | J12: =M11 -> 43530.84 | K12: 0.01 | L12: =IFERROR((J12*K12),"") -> 435.3084 | M12: =IF(N12="","",L12+J12) -> 43966.148 | N12: =SUM(N11+30) -> 45865
A13: =A4 -> PETRICK PESSOAL | B13: =SUMIF(G:G,A13,M:M) -> 75698.21 | H13: 46235 | I13: 11 | J13: =M12 -> 43966.148 | K13: 0.01 | L13: =IFERROR((J13*K13),"") -> 439.66148 | M13: =IF(N13="","",L13+J13) -> 44405.809 | N13: =SUM(N12+30) -> 45895
A14: =A5 -> PETRICK (MÃE) | B14: =SUMIF(G:G,A14,M:M) -> 32449.499 | H14: 46266 | I14: 12 | J14: =M13 -> 44405.809 | K14: 0.01 | L14: =IFERROR((J14*K14),"") -> 444.05809 | M14: =IF(N14="","",L14+J14) -> 44849.868 | N14: =SUM(N13+30) -> 45925
A15: FLÁVIA | B15: =SUMIF(G:G,A15,M:M) -> 0 | H15: 46296 | I15: 13 | J15: =M14 -> 44849.868 | K15: 0.01 | L15: =IFERROR((J15*K15),"") -> 448.49868 | M15: =IF(N15="","",L15+J15) -> 45298.366 | N15: =SUM(N14+30) -> 45955
A16: PETRICK E PEIXOTO | B16: =SUMIF(G:G,A16,M:M) -> 0 | H16: 46327 | I16: 14 | J16: =M15 -> 45298.366 | K16: 0.01 | L16: =IFERROR((J16*K16),"") -> 452.98366 | M16: =IF(N16="","",L16+J16) -> 45751.35 | N16: =SUM(N15+30) -> 45985
A17: TT EMPRÉSTIMO PESSOAL | B17: =SUM(B13:B16) -> 108147.71 | H17: 46357 | I17: 15 | J17: =M16 -> 45751.35 | K17: 0.01 | L17: =IFERROR((J17*K17),"") -> 457.5135 | M17: =IF(N17="","",L17+J17) -> 46208.863 | N17: =SUM(N16+30) -> 46015
G22: =A4 -> PETRICK PESSOAL | H22: TOTAL | M22: =LARGE(M3:M16,1) -> 45751.35
G25: CREDOR | H25: Nome mês | I25: Mês | J25: Valor Inicial | K25: Juros | L25: Vlr Juros | M25: Valor Final | N25: Dt Vlor Final
H26: 45870 | I26: 1 | J26: =B5 -> 30801 | K26: 0.015 | L26: =IFERROR((J26*K26)/30*15," ") -> 231.0075 | M26: =IF(N26="","",L26+J26) -> 31032.007 | N26: 45899
H27: 45901 | I27: 2 | J27: =M26 -> 31032.007 | K27: =K26 -> 0.015 | L27: =IFERROR((J27*K27),"") -> 465.48011 | M27: =IF(N27="","",L27+J27) -> 31497.488 | N27: =SUM(N26+30) -> 45929
H28: 45931 | I28: 3 | J28: =M27 -> 31497.488 | K28: =K27 -> 0.015 | L28: =IFERROR((J28*K28),"") -> 472.46231 | M28: =IF(N28="","",L28+J28) -> 31969.95 | N28: =SUM(N27+30) -> 45959
H29: 45962 | I29: 4 | J29: =M28 -> 31969.95 | K29: =K28 -> 0.015 | L29: =IFERROR((J29*K29),"") -> 479.54925 | M29: =IF(N29="","",L29+J29) -> 32449.499 | N29: =SUM(N28+30) -> 45989
H30: 45992 | I30: 5 | J30: =M29 -> 32449.499 | K30: =K29 -> 0.015 | L30: =IFERROR((J30*K30),"") -> 486.74249 | M30: =IF(N30="","",L30+J30) -> 32936.242 | N30: =SUM(N29+30) -> 46019
G34: =A14 -> PETRICK (MÃE) | H34: TOTAL | M34: =LARGE(M28:M29,1) -> 32449.499
G36: CREDOR | H36: Nome mês | I36: Mês | J36: Valor Inicial | K36: Juros | L36: Vlr Juros | M36: Valor Final | N36: Dt Vlor Final
H37: 45901 | I37: 1 | J37: =B7 -> 28425.5 | K37: 0.015 | L37: =IFERROR((J37*K37)/30*15," ") -> 213.19125 | M37: =IF(N37="","",L37+J37) -> 28638.691 | N37: 45930
H38: 45931 | I38: 2 | J38: =M37 -> 28638.691 | K38: =K37 -> 0.015 | L38: =IFERROR((J38*K38),"") -> 429.58037 | M38: =IF(N38="","",L38+J38) -> 29068.272 | N38: =SUM(N37+30) -> 45960
H39: 45962 | I39: 3 | J39: =M38 -> 29068.272 | K39: =K38 -> 0.015 | L39: =IFERROR((J39*K39),"") -> 436.02407 | M39: =IF(N39="","",L39+J39) -> 29504.296 | N39: =SUM(N38+30) -> 45990
H40: 45992 | I40: 4 | J40: =M39 -> 29504.296 | K40: =K39 -> 0.015 | L40: =IFERROR((J40*K40),"") -> 442.56444 | M40: =IF(N40="","",L40+J40) -> 29946.86 | N40: =SUM(N39+30) -> 46020
H41: 46023 | I41: 5 | J41: =M40 -> 29946.86 | K41: =K40 -> 0.015 | L41: =IFERROR((J41*K41),"") -> 449.2029 | M41: =IF(N41="","",L41+J41) -> 30396.063 | N41: =SUM(N40+30) -> 46050
G45: =A13 -> PETRICK PESSOAL | H45: TOTAL | M45: =LARGE(M39:M40,1) -> 29946.86

Sheet EMPRÉSTIMO PESSOAL PEIXOTO
A1: RACIONAL EMPRESTIMOS E INVESTIMENTO
G2: CREDOR | H2: Nome mês | I2: Mês | J2: Valor Inicial | K2: Juros | L2: Vlr Juros | M2: Valor Final | N2: Dt Vlor Final
A3: QUEM | B3: VALOR | C3: Detatlhes | D3: Mês Emp. | E3: Descrição | H3: 45931 | I3: 1 | J3: =B4 -> 40000 | K3: 0.01 | L3: =IFERROR((J3*K3)/30*15," ") -> 200 | M3: =IF(N3="","",L3+J3) -> 40200 | N3: 45595
A4: PEIXOTO (EVENTOS) | B4: 40000 | C4: Expo Feiras | D4: 45931 | E4: Pagamento com juros de 1% | H4: 45962 | I4: 2 | J4: =M3 -> 40200 | K4: 0.01 | L4: =IFERROR((J4*K4),"") -> 402 | M4: =IF(N4="","",L4+J4) -> 40602 | N4: =SUM(N3+30) -> 45625
A5: PEIXOTO (MEDICAMENTOS) | B5: 30801 | C5: Nutrallis | D5: 45870 | E5: Pagamento com juros de 1% | H5: 45992 | I5: 3 | J5: =M4 -> 40602 | K5: 0.01 | L5: =IFERROR((J5*K5),"") -> 406.02 | M5: =IF(N5="","",L5+J5) -> 41008.02 | N5: =SUM(N4+30) -> 45655
A6: PEIXOTO JEFF (MEDICAMENTE) | B6: 15400 | C6: NUTRALLIS 1ª Formulas | D6: 45870 | H6: 46023 | I6: 4 | J6: =M5 -> 41008.02 | K6: 0.01 | L6: =IFERROR((J6*K6),"") -> 410.0802 | M6: =IF(N6="","",L6+J6) -> 41418.1 | N6: =SUM(N5+30) -> 45685
A7: PEIXOTO JEFF (MEDICAMENTE) | B7: 28425.5 | C7: Nutrallis | D7: 45901 | H7: 46054 | I7: 5 | J7: =M6 -> 41418.1 | K7: 0.01 | L7: =IFERROR((J7*K7),"") -> 414.181 | M7: =IF(N7="","",L7+J7) -> 41832.281 | N7: =SUM(N6+30) -> 45715
B8: =SUM(B4:B5)+B7 -> 99226.5 | H8: 46082 | I8: 6 | J8: =M7 -> 41832.281 | K8: 0.01 | L8: =IFERROR((J8*K8),"") -> 418.32281 | M8: =IF(N8="","",L8+J8) -> 42250.604 | N8: =SUM(N7+30) -> 45745
H9: 46113 | I9: 7 | J9: =M8 -> 42250.604 | K9: 0.01 | L9: =IFERROR((J9*K9),"") -> 422.50604 | M9: =IF(N9="","",L9+J9) -> 42673.11 | N9: =SUM(N8+30) -> 45775
H10: 46143 | I10: 8 | J10: =M9 -> 42673.11 | K10: 0.01 | L10: =IFERROR((J10*K10),"") -> 426.7311 | M10: =IF(N10="","",L10+J10) -> 43099.841 | N10: =SUM(N9+30) -> 45805
A11: QUEM | B11: VALOR Á PAGAR | H11: 46174 | I11: 9 | J11: =M10 -> 43099.841 | K11: 0.01 | L11: =IFERROR((J11*K11),"") -> 430.99841 | M11: =IF(N11="","",L11+J11) -> 43530.84 | N11: =SUM(N10+30) -> 45835
A12: =A4 -> PEIXOTO (EVENTOS) | B12: =SUMIF(G:G,A12,M:M) -> 45751.35 | H12: 46204 | I12: 10 | J12: =M11 -> 43530.84 | K12: 0.01 | L12: =IFERROR((J12*K12),"") -> 435.3084 | M12: =IF(N12="","",L12+J12) -> 43966.148 | N12: =SUM(N11+30) -> 45865
A13: =A5 -> PEIXOTO (MEDICAMENTOS) | B13: =SUMIF(G:G,A13,M:M) -> 31892.973 | H13: 46235 | I13: 11 | J13: =M12 -> 43966.148 | K13: 0.01 | L13: =IFERROR((J13*K13),"") -> 439.66148 | M13: =IF(N13="","",L13+J13) -> 44405.809 | N13: =SUM(N12+30) -> 45895
A14: TT EMPRÉSTIMO PESSOAL | B14: =SUM(B12:B13) -> 77644.322 | H14: 46266 | I14: 12 | J14: =M13 -> 44405.809 | K14: 0.01 | L14: =IFERROR((J14*K14),"") -> 444.05809 | M14: =IF(N14="","",L14+J14) -> 44849.868 | N14: =SUM(N13+30) -> 45925
H15: 46296 | I15: 13 | J15: =M14 -> 44849.868 | K15: 0.01 | L15: =IFERROR((J15*K15),"") -> 448.49868 | M15: =IF(N15="","",L15+J15) -> 45298.366 | N15: =SUM(N14+30) -> 45955
H16: 46327 | I16: 14 | J16: =M15 -> 45298.366 | K16: 0.01 | L16: =IFERROR((J16*K16),"") -> 452.98366 | M16: =IF(N16="","",L16+J16) -> 45751.35 | N16: =SUM(N15+30) -> 45985
H17: 46357 | I17: 15 | J17: =M16 -> 45751.35 | K17: 0.01 | L17: =IFERROR((J17*K17),"") -> 457.5135 | M17: =IF(N17="","",L17+J17) -> 46208.863 | N17: =SUM(N16+30) -> 46015
G21: =A4 -> PEIXOTO (EVENTOS) | H21: TOTAL | M21: =LARGE(M3:M16,1) -> 45751.35
G24: CREDOR | H24: Nome mês | I24: Mês | J24: Valor Inicial | K24: Juros | L24: Vlr Juros | M24: Valor Final | N24: Dt Vlor Final
H25: 45870 | I25: 1 | J25: =B5 -> 30801 | K25: 0.01 | L25: =IFERROR((J25*K25)/30*15," ") -> 154.005 | M25: =IF(N25="","",L25+J25) -> 30955.005 | N25: 45899
H26: 45901 | I26: 2 | J26: =M25 -> 30955.005 | K26: 0.01 | L26: =IFERROR((J26*K26),"") -> 309.55005 | M26: =IF(N26="","",L26+J26) -> 31264.555 | N26: =SUM(N25+30) -> 45929
H27: 45931 | I27: 3 | J27: =M26 -> 31264.555 | K27: 0.01 | L27: =IFERROR((J27*K27),"") -> 312.64555 | M27: =IF(N27="","",L27+J27) -> 31577.201 | N27: =SUM(N26+30) -> 45959
H28: 45962 | I28: 4 | J28: =M27 -> 31577.201 | K28: 0.01 | L28: =IFERROR((J28*K28),"") -> 315.77201 | M28: =IF(N28="","",L28+J28) -> 31892.973 | N28: =SUM(N27+30) -> 45989
H29: 45992 | I29: 5 | J29: =M28 -> 31892.973 | K29: 0.01 | L29: =IFERROR((J29*K29),"") -> 318.92973 | M29: =IF(N29="","",L29+J29) -> 32211.902 | N29: =SUM(N28+30) -> 46019
G33: =A13 -> PEIXOTO (MEDICAMENTOS) | H33: TOTAL | M33: =LARGE(M27:M28,1) -> 31892.973

Sheet EMPRÉSTIMO BROBOND
A1: RACIONAL EMPRESTIMOS E INVESTIMENTO
G2: CREDOR | H2: Nome mês | I2: Mês | J2: Valor Inicial | K2: Juros | L2: Vlr Juros | M2: Valor Final | N2: Dt Vlor Final | Q2: Data Prev. Fech.
A3: QUEM | B3: VALOR | C3: Detatlhes | D3: Mês Emp. | E3: Descrição | H3: Março | I3: 1 | J3: =B4 -> 5000 | K3: 0.03 | L3: =IFERROR((J3*K3)/30*15," ") -> 75 | M3: =IF(N3="","",L3+J3) -> 5075 | N3: =D4 -> 45717
A4: FLÁVIA | B4: 5000 | C4: Brobond | D4: 45717 | E4: Pagamento com juros de 2% | H4: Abril | I4: 2 | J4: =M3 -> 5075 | K4: 0.03 | L4: =IFERROR((J4*K4),"") -> 152.25 | M4: =IF(N4="","",L4+J4) -> 5227.25 | N4: =SUM(N3+30) -> 45747
A5: LU MÃE PETRICK | B5: 30000 | C5: Brobond | D5: 45746 | E5: Pagamento com juros de 2% | H5: Maio | I5: 3 | J5: =M4 -> 5227.25 | K5: 0.03 | L5: =IFERROR((J5*K5),"") -> 156.8175 | M5: =IF(N5="","",L5+J5) -> 5384.0675 | N5: =SUM(N4+30) -> 45777 | Q5: 45807
A6: FLÁVIA | B6: =7000+8000 -> 15000 | C6: Brobond | D6: 45825 | E6: Pagamento com juros de 3% | H6: Junho | I6: 4 | J6: =M5 -> 5384.0675 | K6: 0.03 | L6: =IFERROR((J6*K6),"") -> 161.52202 | M6: =IF(N6="","",L6+J6) -> 5545.5895 | N6: =SUM(N5+30) -> 45807 | Q6: 45838
A7: LU MÃE PETRICK | B7: 15000 | C7: Brobond | D7: 45924 | E7: Pagamento com juros de 3% | H7: Julho | I7: 5 | J7: =M6 -> 5545.5895 | K7: 0.03 | L7: =IFERROR((J7*K7),"") -> 166.36769 | M7: =IF(N7="","",L7+J7) -> 5711.9572 | N7: =SUM(N6+30) -> 45837 | Q7: 45868
A8: FLÁVIA | B8: 2400 | C8: Brobond | D8: 45931 | E8: Pagamento com juros de 3% | H8: Agosto | I8: 6 | J8: =M7 -> 5711.9572 | K8: 0.03 | L8: =IFERROR((J8*K8),"") -> 171.35872 | M8: =IF(N8="","",L8+J8) -> 5883.3159 | N8: =SUM(N7+30) -> 45867 | Q8: 45899
A9: EMPRÉSTIMO MÃE PETRICK | B9: 15000 | C9: Brobond | D9: 45962 | E9: Pagamento com juros de 3% | H9: Setembro | I9: 7 | J9: =M8 -> 5883.3159 | K9: 0.03 | L9: =IFERROR((J9*K9),"") -> 176.49948 | M9: =IF(N9="","",L9+J9) -> 6059.8154 | N9: =SUM(N8+30) -> 45897 | Q9: 45930
A10: PETRICK BROBOND | B10: 10000 | C10: Contas Brobond | D10: 46054 | E10: Pagamento Contas Fev/2026 | H10: Outubro | I10: 8 | J10: =M9 -> 6059.8154 | K10: 0.03 | L10: =IFERROR((J10*K10),"") -> 181.79446 | M10: =IF(N10="","",L10+J10) -> 6241.6099 | N10: =SUM(N9+30) -> 45927 | Q10: 45960
A11: TOTAL EMPRÉSTIMO | B11: =SUM(B4:B9) -> 82400 | H11: Novembro | I11: 9 | J11: =M10 -> 6241.6099 | K11: 0.03 | L11: =IFERROR((J11*K11),"") -> 187.2483 | M11: =IF(N11="","",L11+J11) -> 6428.8582 | N11: =SUM(N10+30) -> 45957 | Q11: 45991
A12: PETRICK MARTINS | B12: 8247 | C12: Brobond | D12: 46082 | E12: Pagamento contas Brobond | H12: Dezembro | I12: 10 | J12: =M11 -> 6428.8582 | K12: 0.03 | L12: =IFERROR((J12*K12),"") -> 192.86574 | M12: =IF(N12="","",L12+J12) -> 6621.7239 | N12: =SUM(N11+30) -> 45987 | Q12: 46021
A13: PETRICK MARTINS | B13: 3470 | C13: Brobnd | D13: 46113 | E13: Pagamentos Contas Brobond
A14: PETRICK MARTINS | B14: 3500 | C14: BROBOND | D14: 46143 | E14: Pagamento contas Brobond
G16: =A4 -> FLÁVIA | H16: TOTAL | M16: =LARGE(M3:M12,1) -> 6621.7239
G19: CREDOR | H19: Nome mês | I19: Mês | J19: Valor Inicial | K19: Juros | L19: Vlr Juros | M19: Valor Final | N19: Dt Vlor Final | Q19: 45838
H20: Março | I20: 1 | J20: =B5 -> 30000 | K20: 0.02 | L20: =IFERROR((J20*K20)/30*15," ") -> 300 | M20: =IF(N20="","",L20+J20) -> 30300 | N20: 45777 | Q20: 45868
H21: Abril | I21: 2 | J21: =M20 -> 30300 | K21: 0.02 | L21: =IFERROR((J21*K21),"") -> 606 | M21: =IF(N21="","",L21+J21) -> 30906 | N21: =SUM(N20+30) -> 45807 | Q21: 45899
H22: Maio | I22: 3 | J22: =M21 -> 30906 | K22: 0.02 | L22: =IFERROR((J22*K22),"") -> 618.12 | M22: =IF(N22="","",L22+J22) -> 31524.12 | N22: =SUM(N21+30) -> 45837 | Q22: 45930
A23: PAGAMENTO COM JUROS | H23: Junho | I23: 4 | J23: =M22 -> 31524.12 | K23: 0.02 | L23: =IFERROR((J23*K23),"") -> 630.4824 | M23: =IF(N23="","",L23+J23) -> 32154.602 | N23: =SUM(N22+30) -> 45867 | Q23: 45960
A24: QUEM | B24: VALOR Á PAGAR | H24: Julho | I24: 5 | J24: =M23 -> 32154.602 | K24: 0.02 | L24: =IFERROR((J24*K24),"") -> 643.09205 | M24: =IF(N24="","",L24+J24) -> 32797.694 | N24: =SUM(N23+30) -> 45897 | Q24: 45991
A25: FLAVIA | B25: =SUMIF(G:G,A25,M:M) -> 21386.713 | H25: Agosto | I25: 6 | J25: =M24 -> 32797.694 | K25: 0.02 | L25: =IFERROR((J25*K25),"") -> 655.95389 | M25: =IF(N25="","",L25+J25) -> 33453.648 | N25: =SUM(N24+30) -> 45927 | Q25: 46021
A26: LU MÃE PETRICK | B26: =SUMIF(G:G,A26,M:M) -> 35501.279 | H26: Setembro | I26: 7 | J26: =M25 -> 33453.648 | K26: 0.02 | L26: =IFERROR((J26*K26),"") -> 669.07297 | M26: =IF(N26="","",L26+J26) -> 34122.721 | N26: =SUM(N25+30) -> 45957
A27: PETRICK (Investidor) Mãe | B27: =SUMIF(G:G,A27,M:M) -> 16152.202 | H27: Outubro | I27: 8 | J27: =M26 -> 34122.721 | K27: 0.02 | L27: =IFERROR((J27*K27),"") -> 682.45443 | M27: =IF(N27="","",L27+J27) -> 34805.176 | N27: =SUM(N26+30) -> 45987
A28: PETRICK PESSOAL | B28: =SUMIF(G:G,A28,M:M) -> #VALUE! | H28: Novembro | I28: 9 | J28: =M27 -> 34805.176 | K28: 0.02 | L28: =IFERROR((J28*K28),"") -> 696.10351 | M28: =IF(N28="","",L28+J28) -> 35501.279 | N28: =SUM(N27+30) -> 46017
A29: TT EMPRÉSTIMO BROBOND | B29: =SUM(B25:B27) -> 73040.194
G32: =A5 -> LU MÃE PETRICK | H32: TOTAL | M32: =LARGE(M20:M28,1) -> 35501.279
G34: CREDOR | H34: Nome mês | I34: Mês | J34: Valor Inicial | K34: Juros | L34: Vlr Juros | M34: Valor Final | N34: Dt Vlor Final
H35: Maio | I35: 1 | J35: =B6 -> 15000 | K35: 0.03 | L35: =IFERROR((J35*K35)/30*15," ") -> 225 | M35: =IF(N35="","",L35+J35) -> 15225 | N35: =D6 -> 45825
H36: Junho | I36: 2 | J36: =M35 -> 15225 | K36: 0.03 | L36: =IFERROR((J36*K36),"") -> 456.75 | M36: =IF(N36="","",L36+J36) -> 15681.75 | N36: =SUM(N35+30) -> 45855
H37: Julho | I37: 3 | J37: =M36 -> 15681.75 | K37: 0.03 | L37: =IFERROR((J37*K37),"") -> 470.4525 | M37: =IF(N37="","",L37+J37) -> 16152.202 | N37: =SUM(N36+30) -> 45885
H38: Agosto | I38: 4 | J38: =M37 -> 16152.202 | K38: 0.03 | L38: =IFERROR((J38*K38),"") -> 484.56607 | M38: =IF(N38="","",L38+J38) -> 16636.769 | N38: =SUM(N37+30) -> 45915
H39: Setembro | I39: 5 | J39: =M38 -> 16636.769 | K39: 0.03 | L39: =IFERROR((J39*K39),"") -> 499.10306 | M39: =IF(N39="","",L39+J39) -> 17135.872 | N39: =SUM(N38+30) -> 45945
H40: Outubro | I40: 6 | J40: =M39 -> 17135.872 | K40: 0.03 | L40: =IFERROR((J40*K40),"") -> 514.07615 | M40: =IF(N40="","",L40+J40) -> 17649.948 | N40: =SUM(N39+30) -> 45975
H41: Novembro | I41: 7 | J41: =M40 -> 17649.948 | K41: 0.03 | L41: =IFERROR((J41*K41),"") -> 529.49843 | M41: =IF(N41="","",L41+J41) -> 18179.446 | N41: =SUM(N40+30) -> 46005
H42: Dezembro | I42: 8 | J42: =M41 -> 18179.446 | K42: 0.03 | L42: =IFERROR((J42*K42),"") -> 545.38339 | M42: =IF(N42="","",L42+J42) -> 18724.83 | N42: =SUM(N41+30) -> 46035
G46: FLAVIA | H46: TOTAL | M46: =LARGE(M35:M42,1) -> 18724.83
G48: CREDOR | H48: Nome mês | I48: Mês | J48: Valor Inicial | K48: Juros | L48: Vlr Juros | M48: Valor Final | N48: Dt Vlor Final
H49: Setembro | I49: 1 | J49: =B7 -> 15000 | K49: 0.03 | L49: =IFERROR((J49*K49)/30*15," ") -> 225 | M49: =IF(N49="","",L49+J49) -> 15225 | N49: 45930
H50: Outubro | I50: 2 | J50: =M49 -> 15225 | K50: 0.03 | L50: =IFERROR((J50*K50),"") -> 456.75 | M50: =IF(N50="","",L50+J50) -> 15681.75 | N50: =N49+30 -> 45960
H51: Novembro | I51: 3 | J51: =M50 -> 15681.75 | K51: 0.03 | L51: =IFERROR((J51*K51),"") -> 470.4525 | M51: =IF(N51="","",L51+J51) -> 16152.202 | N51: =N50+30 -> 45990
H52: Dezembro | I52: 4 | J52: =M51 -> 16152.202 | K52: 0.03 | L52: =IFERROR((J52*K52),"") -> 484.56607 | M52: =IF(N52="","",L52+J52) -> 16636.769 | N52: =N51+30 -> 46020
H53: Janeiro | I53: 5 | J53: =M50 -> 15681.75 | K53: 0.03 | L53: =IFERROR((J53*K53),"") -> 470.4525 | M53: =IF(N53="","",L53+J53) -> 16152.202 | N53: =N52+30 -> 46050
G57: ='EMPRÉSTIMO BROBOND'!A27 -> PETRICK (Investidor) Mãe | H57: TOTAL | M57: =LARGE(M53:M53,1) -> 16152.202
G60: CREDOR | H60: Nome mês | I60: Mês | J60: Valor Inicial | K60: Juros | L60: Vlr Juros | M60: Valor Final | N60: Dt Vlor Final
H61: Outubro | I61: 1 | J61: =B8 -> 2400 | K61: 0.03 | L61: =IFERROR((J61*K61)/30*15," ") -> 36 | M61: =IF(N61="","",L61+J61) -> 2436 | N61: 45960
H62: Novembro | I62: 2 | J62: =M61 -> 2436 | K62: 0.03 | L62: =IFERROR((J62*K62),"") -> 73.08 | M62: =IF(N62="","",L62+J62) -> 2509.08 | N62: 45930
H63: Dezembro | I63: 3 | J63: =M62 -> 2509.08 | K63: 0.03 | L63: =IFERROR((J63*K63),"") -> 75.2724 | M63: =IF(N63="","",L63+J63) -> 2584.3524 | N63: 45960
H64: Janeiro | I64: 4 | J64: =M63 -> 2584.3524 | K64: 0.03 | L64: =IFERROR((J64*K64),"") -> 77.530572 | M64: =IF(N64="","",L64+J64) -> 2661.883 | N64: 45991
G68: =A25 -> FLAVIA | H68: TOTAL | M68: =M64 -> 2661.883
G70: CREDOR | H70: Nome mês | I70: Mês | J70: Valor Inicial | K70: Juros | L70: Vlr Juros | M70: Valor Final | N70: Dt Vlor Final
H71: 45689 | I71: 1 | J71: ='EMPRÉSTIMO PESSOAL PETRICK'!#REF! -> #REF! | K71: 0.015 | L71: =IFERROR((J71*K71)/30*15," ") | M71: =IF(N71="","",L71+J71) -> #VALUE! | N71: 45930
H72: 45717 | I72: 2 | J72: =M71 -> #VALUE! | K72: =K71 -> 0.015 | L72: =IFERROR((J72*K72),"") | M72: =IF(N72="","",L72+J72) -> #VALUE! | N72: =SUM(N71+30) -> 45960
H73: 45748 | I73: 3 | J73: =M72 -> #VALUE! | K73: =K72 -> 0.015 | L73: =IFERROR((J73*K73),"") | M73: =IF(N73="","",L73+J73) -> #VALUE! | N73: =SUM(N72+30) -> 45990
H74: 45778 | I74: 4 | J74: =M73 -> #VALUE! | K74: =K73 -> 0.015 | L74: =IFERROR((J74*K74),"") | M74: =IF(N74="","",L74+J74) -> #VALUE! | N74: =SUM(N73+30) -> 46020
H75: 45809 | I75: 5 | J75: =M74 -> #VALUE! | K75: =K74 -> 0.015 | L75: =IFERROR((J75*K75),"") | M75: =IF(N75="","",L75+J75) -> #VALUE! | N75: =SUM(N74+30) -> 46050
G79: =A28 -> PETRICK PESSOAL | H79: TOTAL | M79: =LARGE(M73:M74,1) -> #VALUE!

Sheet EMPRÉSTIMO EXPOFEIRASCO
A1: RACIONAL EMPRESTIMOS E INVESTIMENTO
G2: CREDOR | H2: Nome mês | I2: Mês | J2: Valor Inicial | K2: Juros | L2: Vlr Juros | M2: Valor Final | N2: Dt Vlor Final
A3: QUEM | B3: VALOR | C3: Detatlhes | D3: Mês Emp. | E3: Descrição | H3: Outubro | I3: 1 | J3: =B4 -> 2000 | K3: 0.03 | L3: =IFERROR((J3*K3)/30*15," ") -> 30 | M3: =IF(N3="","",L3+J3) -> 2030 | N3: =D4 -> 45924
A4: FLAVIA CARTÃO | B4: 2000 | C4: EXPOFEIRAS AGENCIA | D4: 45924 | E4: Pagamento com juros de 2% | H4: Novembro | I4: 2 | J4: =M3 -> 2030 | K4: 0.03 | L4: =IFERROR((J4*K4),"") -> 60.9 | M4: =IF(N4="","",L4+J4) -> 2090.9 | N4: =SUM(N3+30) -> 45954
A5: FLAVIA CARTÃO | B5: 1600 | C5: EXPOFEIRAS AGENCIA | D5: 45931 | E5: Pagamento com juros de 2% | H5: Dezembro | I5: 3 | J5: =M4 -> 2090.9 | K5: 0.03 | L5: =IFERROR((J5*K5),"") -> 62.727 | M5: =IF(N5="","",L5+J5) -> 2153.627 | N5: =SUM(N4+30) -> 45984
A6: CARTÃO FLAVIA | B6: 600 | C6: EXPOFEIRAS AGENCIA | D6: 45964 | E6: Pagamento com juros de 2% | H6: Janeiro | I6: 4 | J6: =M5 -> 2153.627 | K6: 0.03 | L6: =IFERROR((J6*K6),"") -> 64.60881 | M6: =IF(N6="","",L6+J6) -> 2218.2358 | N6: =SUM(N5+30) -> 46014
A7: Mãe Petrick | B7: 6500 | C7: EXPOFEIRAS AGENCIA | D7: 45931 | E7: Pagamento com juros de 2% | G7: FLAVIA | H7: TOTAL | M7: =LARGE(M3:M6,1) -> 2218.2358
A9: Cartão Flávia
A10: TOTAL EMPRÉSTIMO | B10: =SUM(B4:B8) -> 10700 | G10: CREDOR | H10: Nome mês | I10: Mês | J10: Valor Inicial | K10: Juros | L10: Vlr Juros | M10: Valor Final | N10: Dt Vlor Final
H11: Outubro | I11: 1 | J11: =B5 -> 1600 | K11: 0.02 | L11: =IFERROR((J11*K11)/30*15," ") -> 16 | M11: =IF(N11="","",L11+J11) -> 1616 | N11: 45777
H12: Novembro | I12: 2 | J12: =M11 -> 1616 | K12: 0.02 | L12: =IFERROR((J12*K12),"") -> 32.32 | M12: =IF(N12="","",L12+J12) -> 1648.32 | N12: =SUM(N11+30) -> 45807
H13: Dezembro | I13: 3 | J13: =M12 -> 1648.32 | K13: 0.02 | L13: =IFERROR((J13*K13),"") -> 32.9664 | M13: =IF(N13="","",L13+J13) -> 1681.2864 | N13: =SUM(N12+30) -> 45837
A14: PAGAMENTO COM JUROS | H14: Janeiro | I14: 4 | J14: =M13 -> 1681.2864 | K14: 0.02 | L14: =IFERROR((J14*K14),"") -> 33.625728 | M14: =IF(N14="","",L14+J14) -> 1714.9121 | N14: =SUM(N13+30) -> 45867
A15: QUEM | B15: VALOR Á PAGAR | G15: FLAVIA | H15: TOTAL | M15: =M14 -> 1714.9121
A16: FLAVIA | B16: =SUMIF(G:G,A16,M:M) -> 4682.1411
A17: LU MÃE PETRICK | B17: =SUMIF(G:G,A17,M:M) -> 0 | G17: CREDOR | H17: Nome mês | I17: Mês | J17: Valor Inicial | K17: Juros | L17: Vlr Juros | M17: Valor Final | N17: Dt Vlor Final
A18: PETRICK (Investidor) Mãe | B18: =SUMIF(G:G,A18,M:M) -> 6999.2878 | H18: Novembro | I18: 1 | J18: =B6 -> 600 | K18: 0.03 | L18: =IFERROR((J18*K18)/30*15," ") -> 9 | M18: =IF(N18="","",L18+J18) -> 609 | N18: =D6 -> 45964
A19: TT EMPRÉSTIMO BROBOND | B19: =SUM(B16:B18) -> 11681.429 | H19: Dezembro | I19: 2 | J19: =M18 -> 609 | K19: 0.03 | L19: =IFERROR((J19*K19),"") -> 18.27 | M19: =IF(N19="","",L19+J19) -> 627.27 | N19: =SUM(N18+30) -> 45994
H20: Janeiro | I20: 3 | J20: =M19 -> 627.27 | K20: 0.03 | L20: =IFERROR((J20*K20),"") -> 18.8181 | M20: =IF(N20="","",L20+J20) -> 646.0881 | N20: =SUM(N19+30) -> 46024
H21: Fevereiro | I21: 4 | J21: =M20 -> 646.0881 | K21: 0.03 | L21: =IFERROR((J21*K21),"") -> 19.382643 | M21: =IF(N21="","",L21+J21) -> 665.47074 | N21: =SUM(N20+30) -> 46054
H22: Março | I22: 5 | J22: =M21 -> 665.47074 | K22: 0.03 | L22: =IFERROR((J22*K22),"") -> 19.964122 | M22: =IF(N22="","",L22+J22) -> 685.43487 | N22: =SUM(N21+30) -> 46084
H23: Abril | I23: 6 | J23: =M22 -> 685.43487 | K23: 0.03 | L23: =IFERROR((J23*K23),"") -> 20.563046 | M23: =IF(N23="","",L23+J23) -> 705.99791 | N23: =SUM(N22+30) -> 46114
H24: Maio | I24: 7 | J24: =M23 -> 705.99791 | K24: 0.03 | L24: =IFERROR((J24*K24),"") -> 21.179937 | M24: =IF(N24="","",L24+J24) -> 727.17785 | N24: =SUM(N23+30) -> 46144
H25: Junho | I25: 8 | J25: =M24 -> 727.17785 | K25: 0.03 | L25: =IFERROR((J25*K25),"") -> 21.815335 | M25: =IF(N25="","",L25+J25) -> 748.99318 | N25: =SUM(N24+30) -> 46174
G26: FLAVIA | H26: TOTAL | M26: =LARGE(M18:M25,1) -> 748.99318
G28: CREDOR | H28: Nome mês | I28: Mês | J28: Valor Inicial | K28: Juros | L28: Vlr Juros | M28: Valor Final | N28: Dt Vlor Final
H29: Outubro | I29: 1 | J29: =B7 -> 6500 | K29: 0.03 | L29: =IFERROR((J29*K29)/30*15," ") -> 97.5 | M29: =IF(N29="","",L29+J29) -> 6597.5 | N29: 45899
H30: Novembro | I30: 2 | J30: =M29 -> 6597.5 | K30: 0.03 | L30: =IFERROR((J30*K30),"") -> 197.925 | M30: =IF(N30="","",L30+J30) -> 6795.425 | N30: 45930
H31: Dezembro | I31: 3 | J31: =M30 -> 6795.425 | K31: 0.03 | L31: =IFERROR((J31*K31),"") -> 203.86275 | M31: =IF(N31="","",L31+J31) -> 6999.2878 | N31: 45960
H32: Janeiro | I32: 4 | J32: =M31 -> 6999.2878 | K32: 0.03 | L32: =IFERROR((J32*K32),"") -> 209.97863 | M32: =IF(N32="","",L32+J32) -> 7209.2664 | N32: 45991
H33: Fevereiro | I33: 5 | J33: =M30 -> 6795.425 | K33: 0.03 | L33: =IFERROR((J33*K33),"") -> 203.86275 | M33: =IF(N33="","",L33+J33) -> 6999.2878 | N33: 46021
G34: ='EMPRÉSTIMO EXPOFEIRASCO'!A18 -> PETRICK (Investidor) Mãe | H34: TOTAL | M34: =LARGE(M33:M33,1) -> 6999.2878
G37: CREDOR | H37: Nome mês | I37: Mês | J37: Valor Inicial | K37: Juros | L37: Vlr Juros | M37: Valor Final | N37: Dt Vlor Final
H38: Outubro | I38: 1 | J38: =B8 -> 0 | K38: 0.03 | L38: =IFERROR((J38*K38)/30*15," ") -> 0 | M38: =IF(N38="","",L38+J38) -> 0 | N38: 45960
H39: Novembro | I39: 2 | J39: =M38 -> 0 | K39: 0.03 | L39: =IFERROR((J39*K39),"") -> 0 | M39: =IF(N39="","",L39+J39) -> 0 | N39: 45930
H40: Dezembro | I40: 3 | J40: =M39 -> 0 | K40: 0.03 | L40: =IFERROR((J40*K40),"") -> 0 | M40: =IF(N40="","",L40+J40) -> 0 | N40: 45960
H41: Janeiro | I41: 4 | J41: =M40 -> 0 | K41: 0.03 | L41: =IFERROR((J41*K41),"") -> 0 | M41: =IF(N41="","",L41+J41) -> 0 | N41: 45991
G42: =A16 -> FLAVIA | H42: TOTAL | M42: =M41 -> 0

Sheet EMPRÉSTIMO INSTITUTO
A1: RACIONAL EMPRESTIMOS E INVESTIMENTO
G2: CREDOR | H2: Nome mês | I2: Mês | J2: Valor Inicial | K2: Juros | L2: Vlr Juros | M2: Valor Final | N2: Dt Vlor Final
A3: QUEM | B3: VALOR | C3: Detatlhes | D3: Mês Emp. | E3: Descrição | H3: Outubro | I3: 1 | J3: =B4 -> 54000 | K3: 0.03 | L3: =IFERROR((J3*K3)/30*15," ") -> 810 | M3: =IF(N3="","",L3+J3) -> 54810 | N3: =D4 -> 46094
A4: Peixoto Gado | B4: 54000 | C4: 20 Garrotes | D4: 46094 | E4: Pagamento com juros de @ do dia endorda diária até a data | H4: Novembro | I4: 2 | J4: =M3 -> 54810 | K4: 0.03 | L4: =IFERROR((J4*K4),"") -> 1644.3 | M4: =IF(N4="","",L4+J4) -> 56454.3 | N4: =SUM(N3+30) -> 46124
A5: Jefferson | B5: 55000 | C5: Pai carro | D5: 45931 | E5: carro 44k mae petrick 13 mil reais | H5: Dezembro | I5: 3 | J5: =M4 -> 56454.3 | K5: 0.03 | L5: =IFERROR((J5*K5),"") -> 1693.629 | M5: =IF(N5="","",L5+J5) -> 58147.929 | N5: =SUM(N4+30) -> 46154
A6: Petrick | B6: 54000 | C6: Petrick Pessoal | D6: 45964 | E6: Pagamento com juros de 2% | H6: Janeiro | I6: 4 | J6: =M5 -> 58147.929 | K6: 0.03 | L6: =IFERROR((J6*K6),"") -> 1744.4379 | M6: =IF(N6="","",L6+J6) -> 59892.367 | N6: =SUM(N5+30) -> 46184
D7: 45931 | E7: Pagamento com juros de 2% | G7: FLAVIA | H7: TOTAL | M7: =LARGE(M3:M6,1) -> 59892.367
A10: TOTAL EMPRÉSTIMO | B10: =SUM(B4:B8) -> 163000 | G10: CREDOR | H10: Nome mês | I10: Mês | J10: Valor Inicial | K10: Juros | L10: Vlr Juros | M10: Valor Final | N10: Dt Vlor Final
H11: Outubro | I11: 1 | J11: =B5 -> 55000 | K11: 0.02 | L11: =IFERROR((J11*K11)/30*15," ") -> 550 | M11: =IF(N11="","",L11+J11) -> 55550 | N11: 45777
H12: Novembro | I12: 2 | J12: =M11 -> 55550 | K12: 0.02 | L12: =IFERROR((J12*K12),"") -> 1111 | M12: =IF(N12="","",L12+J12) -> 56661 | N12: =SUM(N11+30) -> 45807
H13: Dezembro | I13: 3 | J13: =M12 -> 56661 | K13: 0.02 | L13: =IFERROR((J13*K13),"") -> 1133.22 | M13: =IF(N13="","",L13+J13) -> 57794.22 | N13: =SUM(N12+30) -> 45837
A14: PAGAMENTO COM JUROS | H14: Janeiro | I14: 4 | J14: =M13 -> 57794.22 | K14: 0.02 | L14: =IFERROR((J14*K14),"") -> 1155.8844 | M14: =IF(N14="","",L14+J14) -> 58950.104 | N14: =SUM(N13+30) -> 45867
A15: QUEM | B15: VALOR Á PAGAR | G15: FLAVIA | H15: TOTAL | M15: =M14 -> 58950.104
B16: =SUMIF(G:G,A16,M:M) -> 0
B17: =SUMIF(G:G,A17,M:M) -> 0 | G17: CREDOR | H17: Nome mês | I17: Mês | J17: Valor Inicial | K17: Juros | L17: Vlr Juros | M17: Valor Final | N17: Dt Vlor Final
B18: =SUMIF(G:G,A18,M:M) -> 0 | H18: Novembro | I18: 1 | J18: =B6 -> 54000 | K18: 0.03 | L18: =IFERROR((J18*K18)/30*15," ") -> 810 | M18: =IF(N18="","",L18+J18) -> 54810 | N18: =D6 -> 45964
A19: TT EMPRÉSTIMO BROBOND | B19: =SUM(B16:B18) -> 0 | H19: Dezembro | I19: 2 | J19: =M18 -> 54810 | K19: 0.03 | L19: =IFERROR((J19*K19),"") -> 1644.3 | M19: =IF(N19="","",L19+J19) -> 56454.3 | N19: =SUM(N18+30) -> 45994
H20: Janeiro | I20: 3 | J20: =M19 -> 56454.3 | K20: 0.03 | L20: =IFERROR((J20*K20),"") -> 1693.629 | M20: =IF(N20="","",L20+J20) -> 58147.929 | N20: =SUM(N19+30) -> 46024
H21: Fevereiro | I21: 4 | J21: =M20 -> 58147.929 | K21: 0.03 | L21: =IFERROR((J21*K21),"") -> 1744.4379 | M21: =IF(N21="","",L21+J21) -> 59892.367 | N21: =SUM(N20+30) -> 46054
H22: Março | I22: 5 | J22: =M21 -> 59892.367 | K22: 0.03 | L22: =IFERROR((J22*K22),"") -> 1796.771 | M22: =IF(N22="","",L22+J22) -> 61689.138 | N22: =SUM(N21+30) -> 46084
H23: Abril | I23: 6 | J23: =M22 -> 61689.138 | K23: 0.03 | L23: =IFERROR((J23*K23),"") -> 1850.6741 | M23: =IF(N23="","",L23+J23) -> 63539.812 | N23: =SUM(N22+30) -> 46114
H24: Maio | I24: 7 | J24: =M23 -> 63539.812 | K24: 0.03 | L24: =IFERROR((J24*K24),"") -> 1906.1944 | M24: =IF(N24="","",L24+J24) -> 65446.006 | N24: =SUM(N23+30) -> 46144
H25: Junho | I25: 8 | J25: =M24 -> 65446.006 | K25: 0.03 | L25: =IFERROR((J25*K25),"") -> 1963.3802 | M25: =IF(N25="","",L25+J25) -> 67409.387 | N25: =SUM(N24+30) -> 46174
G26: FLAVIA | H26: TOTAL | M26: =LARGE(M18:M25,1) -> 67409.387
G28: CREDOR | H28: Nome mês | I28: Mês | J28: Valor Inicial | K28: Juros | L28: Vlr Juros | M28: Valor Final | N28: Dt Vlor Final
H29: Outubro | I29: 1 | J29: =B7 -> 0 | K29: 0.03 | L29: =IFERROR((J29*K29)/30*15," ") -> 0 | M29: =IF(N29="","",L29+J29) -> 0 | N29: 45899
H30: Novembro | I30: 2 | J30: =M29 -> 0 | K30: 0.03 | L30: =IFERROR((J30*K30),"") -> 0 | M30: =IF(N30="","",L30+J30) -> 0 | N30: 45930
H31: Dezembro | I31: 3 | J31: =M30 -> 0 | K31: 0.03 | L31: =IFERROR((J31*K31),"") -> 0 | M31: =IF(N31="","",L31+J31) -> 0 | N31: 45960
H32: Janeiro | I32: 4 | J32: =M31 -> 0 | K32: 0.03 | L32: =IFERROR((J32*K32),"") -> 0 | M32: =IF(N32="","",L32+J32) -> 0 | N32: 45991
H33: Fevereiro | I33: 5 | J33: =M30 -> 0 | K33: 0.03 | L33: =IFERROR((J33*K33),"") -> 0 | M33: =IF(N33="","",L33+J33) -> 0 | N33: 46021
G34: ='EMPRÉSTIMO INSTITUTO'!A18 -> 0 | H34: TOTAL | M34: =LARGE(M33:M33,1) -> 0
G37: CREDOR | H37: Nome mês | I37: Mês | J37: Valor Inicial | K37: Juros | L37: Vlr Juros | M37: Valor Final | N37: Dt Vlor Final
H38: Outubro | I38: 1 | J38: =B8 -> 0 | K38: 0.03 | L38: =IFERROR((J38*K38)/30*15," ") -> 0 | M38: =IF(N38="","",L38+J38) -> 0 | N38: 45960
H39: Novembro | I39: 2 | J39: =M38 -> 0 | K39: 0.03 | L39: =IFERROR((J39*K39),"") -> 0 | M39: =IF(N39="","",L39+J39) -> 0 | N39: 45930
H40: Dezembro | I40: 3 | J40: =M39 -> 0 | K40: 0.03 | L40: =IFERROR((J40*K40),"") -> 0 | M40: =IF(N40="","",L40+J40) -> 0 | N40: 45960
H41: Janeiro | I41: 4 | J41: =M40 -> 0 | K41: 0.03 | L41: =IFERROR((J41*K41),"") -> 0 | M41: =IF(N41="","",L41+J41) -> 0 | N41: 45991
G42: =A16 -> 0 | H42: TOTAL | M42: =M41 -> 0

Sheet Planilha1
